jupyterlab_exam_submission/_version.py
jupyterlab_exam_submission-4.0.0.data/data/share/jupyter/labextensions/jupyterlab_exam_submission/install.json
jupyterlab_exam_submission-4.0.0.dist-info/METADATA
jupyterlab_exam_submission-4.0.0.dist-info/WHEEL
jupyterlab_exam_submission-4.0.0.dist-info/licenses/LICENSE
jupyterlab_exam_submission-4.0.0.dist-info/RECORD
